{
  "company_id": "netflix",
  "title": "Netflix Q3 2024 Earnings Call",
  "datetime": "2024-10-15T21:00:00Z",
  "period": "CY2024_Q3",
  "location": "Los Gatos, CA",
  "url": "https://ir.netflix.net/",
  "turns": [
    {
      "speaker_id": "greg-peters",
      "speaker_name": "Greg Peters",
      "speaker_role": "Co-CEO",
      "timestamp": "00:01:00",
      "text": "Q3 was another strong quarter. We added 5.07 million paid subscribers to reach 282.7 million. Revenue was $9.83 billion, up 15% year-over-year, at the top of our guidance range. Operating margin was 30%, significantly above our 28% guidance. We are now comfortable saying we will reach 300 million subscribers by end of Q4 2024. Live events are performing better than expected — the Jake Paul vs Mike Tyson boxing event in November will be the largest live streaming event in history."
    },
    {
      "speaker_id": "spencer-neumann",
      "speaker_name": "Spencer Neumann",
      "speaker_role": "CFO",
      "timestamp": "00:18:00",
      "text": "Operating income of $2.9 billion represents a 30% operating margin, well above guidance. For Q4, we expect revenue of $10.1 billion and an operating margin of 22%, reflecting content investments. Full year 2024 operating margin remains guided to 26%. We expect 2025 revenue growth of 11 to 13% and an operating margin of 28 to 29%."
    },
    {
      "speaker_id": "operator",
      "speaker_name": "Operator",
      "speaker_role": "Operator",
      "timestamp": "00:36:00",
      "text": "Our next question comes from Mark Mahaney at Evercore ISI."
    },
    {
      "speaker_id": "analyst-mark-mahaney",
      "speaker_name": "Mark Mahaney",
      "speaker_role": "Analyst",
      "timestamp": "00:36:20",
      "text": "Spencer, how should we think about the trajectory of advertising revenue as a percentage of total revenue, and when does it become a meaningful contributor?"
    }
  ],
  "statements": [
    {
      "id": "NFLX-CY2024Q3-001",
      "turn_index": 0,
      "claim": "Q3 2024 revenue was $9.83 billion with a 30% operating margin, above guidance of $9.825B and 28%.",
      "categorizations": [
        "revenue_trajectory_specific",
        "margin_trajectory_specific"
      ],
      "commitment_tags": [
        "explicit_forward_or_present_tense_assertion",
        "verifiable_against_subsequent_disclosure_or_financial_statement",
        "attributable_to_specific_speaker"
      ],
      "hedging": "unhedged",
      "resolution": {
        "finding": "validated"
      }
    },
    {
      "id": "NFLX-CY2024Q3-002",
      "turn_index": 0,
      "claim": "Netflix will reach 300 million subscribers by end of Q4 2024.",
      "categorizations": [
        "operational_metric_specific"
      ],
      "commitment_tags": [
        "explicit_forward_or_present_tense_assertion",
        "verifiable_against_subsequent_disclosure_or_financial_statement",
        "attributable_to_specific_speaker",
        "falsifiable_within_eight_quarter_window"
      ],
      "hedging": "unhedged",
      "resolution": {
        "finding": "unresolved"
      }
    },
    {
      "id": "NFLX-CY2024Q3-003",
      "turn_index": 1,
      "claim": "2025 revenue will grow 11 to 13% with an operating margin of 28 to 29%.",
      "categorizations": [
        "revenue_trajectory_specific",
        "margin_trajectory_specific"
      ],
      "commitment_tags": [
        "explicit_forward_or_present_tense_assertion",
        "verifiable_against_subsequent_disclosure_or_financial_statement",
        "falsifiable_within_eight_quarter_window"
      ],
      "hedging": "unhedged",
      "resolution": {
        "finding": "unresolved"
      }
    },
    {
      "id": "NFLX-CY2024Q3-004",
      "turn_index": 0,
      "claim": "The Jake Paul vs Mike Tyson boxing event will be the largest live streaming event in history.",
      "categorizations": [
        "operational_metric_specific",
        "competitive_or_market_position_claim"
      ],
      "commitment_tags": [
        "explicit_forward_or_present_tense_assertion",
        "verifiable_against_subsequent_disclosure_or_financial_statement",
        "falsifiable_within_eight_quarter_window"
      ],
      "hedging": "softly_hedged",
      "resolution": {
        "finding": "validated"
      }
    },
    {
      "id": "NFLX-CY2024Q3-005",
      "turn_index": 1,
      "claim": "Q4 2024 revenue guidance is $10.1 billion with an operating margin of 22%.",
      "categorizations": [
        "revenue_trajectory_specific",
        "margin_trajectory_specific"
      ],
      "commitment_tags": [
        "explicit_forward_or_present_tense_assertion",
        "verifiable_against_subsequent_disclosure_or_financial_statement",
        "falsifiable_within_eight_quarter_window"
      ],
      "hedging": "unhedged",
      "resolution": {
        "finding": "unresolved"
      }
    }
  ]
}